telegramdb/__init__.py
telegramdb/constants.py
telegramdb/database.py
telegramdb/exceptions.py
TelegramDB-1.0.0.dist-info/LICENSE
TelegramDB-1.0.0.dist-info/METADATA
TelegramDB-1.0.0.dist-info/WHEEL
TelegramDB-1.0.0.dist-info/top_level.txt
TelegramDB-1.0.0.dist-info/RECORD
