Metadata-Version: 2.1
Name: TelegramDB
Version: 1.0.0
Summary: A library that uses your telegram account as a database for your project.
Home-page: https://github.com/AnimeKaizoku/TelegramDB
Author: Anony
Author-email: contact@anonyindian.me
License: GPLv3
Platform: UNKNOWN
Classifier: Development Status :: 4 - Beta
Classifier: Intended Audience :: Developers
Classifier: License :: OSI Approved :: GNU General Public License v3 (GPLv3)
Classifier: Programming Language :: Python
Classifier: Programming Language :: Python :: 3
Classifier: Programming Language :: Python :: 3.6
Classifier: Programming Language :: Python :: 3.7
Classifier: Programming Language :: Python :: 3.8
Classifier: Programming Language :: Python :: 3.9
Classifier: Programming Language :: Python :: Implementation :: CPython
Classifier: Typing :: Typed
Requires-Python: >=3.6
Requires-Dist: nest-asyncio (==1.5.6)
Requires-Dist: pyrogram (==2.0.103)
Requires-Dist: telethon (==1.28.5)
Requires-Dist: tgcrypto (==1.2.5)
